arrayloaders/__init__.py
arrayloaders/io/__init__.py
arrayloaders/io/dask_loader.py
arrayloaders/io/datamodules.py
arrayloaders/io/store_creation.py
arrayloaders/io/utils.py
arrayloaders/io/zarr_loader.py
arrayloaders-0.0.3.dist-info/LICENSE
arrayloaders-0.0.3.dist-info/WHEEL
arrayloaders-0.0.3.dist-info/METADATA
arrayloaders-0.0.3.dist-info/RECORD
