Metadata-Version: 2.3
Name: arrayloaders
Version: 0.0.3
Summary: Modlyn.
Author-email: Lamin Labs <open-source@lamin.ai>
Requires-Python: >=3.11,<3.13
Requires-Dist: anndata[lazy]>=0.12.0rc1
Requires-Dist: zarr>=3
Requires-Dist: lightning
Requires-Dist: torch
Requires-Dist: dask[array]
Requires-Dist: tqdm
Requires-Dist: universal_pathlib>=0.2.6
Requires-Dist: zarrs ; extra == "dev"
Requires-Dist: scipy>1.15.0 ; extra == "dev"
Requires-Dist: lamindb ; extra == "dev"
Requires-Dist: pre-commit ; extra == "dev"
Requires-Dist: nox ; extra == "dev"
Requires-Dist: pytest>=6.0 ; extra == "dev"
Requires-Dist: pytest-cov ; extra == "dev"
Requires-Dist: nbproject_test ; extra == "dev"
Project-URL: Home, https://github.com/laminlabs/arrayloaders
Provides-Extra: dev
